LICENSE
README.rst
gswrap_meta.py
setup.py
benchmark/__init__.py
benchmark/main.py
gs_wrap.egg-info/PKG-INFO
gs_wrap.egg-info/SOURCES.txt
gs_wrap.egg-info/dependency_links.txt
gs_wrap.egg-info/requires.txt
gs_wrap.egg-info/top_level.txt
gswrap/__init__.py
gswrap/py.typed