Metadata-Version: 2.1
Name: gs-wrap
Version: 1.0.5
Summary: gs-wrap wraps Google Cloud Storage API for multi-threaded data manipulations.
Home-page: https://github.com/Parquery/gs-wrap
Author: Selim Naji, Adam Radomski and Marko Ristin
Author-email: selim.naji@parquery.com, adam.radomski@parquery.com, marko.ristin@gmail.com
License: License :: OSI Approved :: MIT License
Keywords: gsutil google cloud storage wrap
Platform: UNKNOWN
Classifier: Development Status :: 5 - Production/Stable
Classifier: Intended Audience :: Developers
Classifier: License :: OSI Approved :: MIT License
Classifier: Programming Language :: Python :: 3.5
Provides-Extra: dev
